LICENSE
antares_client-1.13.0.dist-info/METADATA
antares_client-1.13.0.dist-info/WHEEL
antares_client-1.13.0.dist-info/entry_points.txt
antares_client-1.13.0.dist-info/licenses/LICENSE
antares_client/__init__.py
antares_client/_api/__init__.py
antares_client/_api/api.py
antares_client/_api/fields.py
antares_client/_api/schemas.py
antares_client/certificates/kafka-ca.pem
antares_client/cli/__init__.py
antares_client/cli/cli.py
antares_client/config.py
antares_client/exceptions.py
antares_client/models.py
antares_client/search.py
antares_client/stream.py
antares_client/utils.py
antares_client-1.13.0.dist-info/RECORD
