Metadata-Version: 2.1
Name: antares-client
Version: 1.13.0
Summary: A light-weight client for receiving alerts from ANTARES.
Keywords: antares
Author-Email: NSF NOIRLab ANTARES Team <antares@noirlab.edu>
Maintainer-Email: NSF NOIRLab ANTARES Team <antares@noirlab.edu>
License: MIT License
Classifier: License :: OSI Approved :: BSD License
Classifier: Programming Language :: Python :: 3.9
Project-URL: Homepage, https://gitlab.com/nsf-noirlab/csdc/antares/client
Project-URL: Documentation, https://nsf-noirlab.gitlab.io/csdc/antares/client
Project-URL: Bug Reports, https://gitlab.com/nsf-noirlab/csdc/antares/client/-/issues
Project-URL: Source, https://gitlab.com/nsf-noirlab/csdc/antares/client
Requires-Python: >=3.9
Requires-Dist: astropy
Requires-Dist: bson
Requires-Dist: click
Requires-Dist: marshmallow<4,>=3.6
Requires-Dist: marshmallow-jsonapi>=0.23
Requires-Dist: numpy
Requires-Dist: pandas
Requires-Dist: requests
Requires-Dist: typing-extensions
Requires-Dist: astropy-healpix
Provides-Extra: dev
Requires-Dist: black; extra == "dev"
Requires-Dist: pylint; extra == "dev"
Requires-Dist: isort; extra == "dev"
Provides-Extra: test
Requires-Dist: coverage==7.2.7; extra == "test"
Requires-Dist: pytest; extra == "test"
Requires-Dist: pytest-cov; extra == "test"
Requires-Dist: requests-mock; extra == "test"
Provides-Extra: subscriptions
Requires-Dist: confluent_kafka==1.7.0; extra == "subscriptions"
Provides-Extra: docs
Requires-Dist: sphinx; extra == "docs"
Requires-Dist: sphinx-click; extra == "docs"
